thecobs/Constants.py
thecobs/CoulombFunctions.py
thecobs/FiniteSize.py
thecobs/Functions.py
thecobs/Generator.py
thecobs/Screening.py
thecobs/SpectralFunctions.py
thecobs/__init__.py
thecobs/data/ExchangeData.dat
thecobs/data/ExchangeDataSimkovic.dat
thecobs/data/__init__.py
thecobs-0.0.21.dist-info/METADATA
thecobs-0.0.21.dist-info/WHEEL
thecobs-0.0.21.dist-info/licenses/LICENSE
thecobs-0.0.21.dist-info/RECORD
