Metadata-Version: 2.1
Name: thecobs
Version: 0.0.21
Summary: A package to calculate precise beta spectrum shapes
Project-URL: Homepage, https://github.com/leenderthayen/thecobs
Project-URL: Bug Tracker, https://github.com/leenderthayen/thecobs/issues
Author-email: Leendert Hayen <leendert.hayen@gmail.com>
License-File: LICENSE
Classifier: License :: OSI Approved :: MIT License
Classifier: Operating System :: OS Independent
Classifier: Programming Language :: Python :: 3
Requires-Python: >=3.7
Requires-Dist: numpy~=1.24.1
Requires-Dist: pandas~=1.5.3
Requires-Dist: scipy~=1.10.0
